{
  "data": {
    "type": "nodes",
    "attributes": {
      "title": "HEXA-RTSC: Room-Temperature Superconductor Architecture and 12 Derived Products (n=6 Framework)",
      "description": "Theoretical architecture for room-temperature superconductivity (Tc=300K, 1 atm) based on the number-theoretic identity σ(n)·φ(n)=n·τ(n)=24 uniquely satisfied at n=6. This dataset contains:\n\n1. **Core Architecture** (goal.md): 8-stage synthesis pipeline with 91 parameters (87% EXACT)\n2. **12 Derived Product Designs**:\n   - Lossless Power Grid (송전손실 0%)\n   - Helium-Free MRI (촬영비 1/5)\n   - RT Quantum Computer (144 logical qubits, desktop-size)\n   - Superconducting CPU (1/1000 power consumption)\n   - RT EV Motor (99.9% efficiency)\n   - RT Maglev Transport (건설비 1/5)\n   - RT-SMES Energy Storage (grid-scale)\n   - Tabletop Fusion Reactor (1/6 ITER size)\n   - Space Colonization Systems\n   - AGI Hardware Architecture (HEXA-AGI)\n   - UFO/Flying Saucer Propulsion\n   - Immortality Medicine\n3. **Verification Scripts**: 13 Python scripts confirming all 937/938 EXACT parameter matches\n\nTotal: 938 parameters, 937 EXACT n=6 matches, 13 verified products at Alien Index 🛸10.",
      "category": "project",
      "tags": [
        "room-temperature-superconductor",
        "number-theory",
        "n6-framework",
        "materials-science",
        "condensed-matter-physics",
        "superconductivity",
        "computational-design",
        "HEXA-RTSC",
        "open-science"
      ]
    }
  },
  "osf_metadata": {
    "node_license": {
      "license_id": "CC-By Attribution 4.0 International"
    },
    "subjects": [
      ["Physical Sciences and Mathematics", "Condensed Matter Physics"],
      ["Physical Sciences and Mathematics", "Materials Science and Engineering"],
      ["Engineering", "Electrical and Computer Engineering"]
    ],
    "affiliated_institutions": [],
    "wiki_home": "# HEXA-RTSC Dataset\n\nRoom-temperature superconductor architecture derived from n=6 number-theoretic framework.\n\nSee goal.md for the core 8-stage pipeline.\nEach product has a .md design document and a -verify.py validation script."
  },
  "files_manifest": [
    {"path": "goal.md", "description": "Core HEXA-RTSC 8-stage architecture (91 params, 87% EXACT)"},
    {"path": "agi-architecture.md", "description": "HEXA-AGI: SC-CPU + QC + 17 AI techniques convergence"},
    {"path": "agi-architecture-verify.py", "description": "AGI architecture verification (196 params)"},
    {"path": "helium-free-mri.md", "description": "Helium-free MRI system design"},
    {"path": "helium-free-mri-verify.py", "description": "MRI parameter verification"},
    {"path": "immortality-medicine.md", "description": "SC-based medical longevity systems"},
    {"path": "lossless-power-grid.md", "description": "Zero-loss power transmission grid"},
    {"path": "lossless-power-grid-verify.py", "description": "Power grid parameter verification"},
    {"path": "rt-ev-motor.md", "description": "Room-temperature SC EV motor (99.9% efficiency)"},
    {"path": "rt-ev-motor-verify.py", "description": "EV motor parameter verification"},
    {"path": "rt-maglev-transport.md", "description": "RT maglev transport system"},
    {"path": "rt-maglev-transport-verify.py", "description": "Maglev parameter verification"},
    {"path": "rt-quantum-computer.md", "description": "Desktop-size quantum computer (144 qubits)"},
    {"path": "rt-quantum-computer-verify.py", "description": "Quantum computer parameter verification"},
    {"path": "rt-smes-storage.md", "description": "Superconducting magnetic energy storage"},
    {"path": "rt-smes-verify.py", "description": "SMES parameter verification"},
    {"path": "space-colonization.md", "description": "SC-based space colonization systems"},
    {"path": "space-colonization-verify.py", "description": "Space systems parameter verification"},
    {"path": "superconducting-cpu.md", "description": "SC-CPU: 1/1000 power consumption processor"},
    {"path": "superconducting-cpu-verify.py", "description": "SC-CPU parameter verification"},
    {"path": "tabletop-fusion.md", "description": "Compact fusion reactor (1/6 ITER size)"},
    {"path": "tabletop-fusion-verify.py", "description": "Fusion reactor parameter verification"},
    {"path": "ufo-flying-saucer.md", "description": "SC propulsion / flying saucer design"},
    {"path": "verify_alien10.py", "description": "Master verification: all products 🛸10"},
    {"path": "verify_ufo.py", "description": "UFO propulsion parameter verification"}
  ],
  "statistics": {
    "total_products": 12,
    "total_parameters": 938,
    "exact_matches": 937,
    "exact_rate": "99.9%",
    "verification_scripts": 13,
    "alien_index": 10
  }
}
